odoo/addons/hr_expense_widget_o2m/README.rst
odoo/addons/hr_expense_widget_o2m/__init__.py
odoo/addons/hr_expense_widget_o2m/__manifest__.py
odoo/addons/hr_expense_widget_o2m/i18n/es.po
odoo/addons/hr_expense_widget_o2m/i18n/hr_expense_widget_o2m.pot
odoo/addons/hr_expense_widget_o2m/i18n/it.po
odoo/addons/hr_expense_widget_o2m/models/__init__.py
odoo/addons/hr_expense_widget_o2m/models/res_config_settings.py
odoo/addons/hr_expense_widget_o2m/readme/CONFIGURE.rst
odoo/addons/hr_expense_widget_o2m/readme/CONTRIBUTORS.rst
odoo/addons/hr_expense_widget_o2m/readme/DESCRIPTION.rst
odoo/addons/hr_expense_widget_o2m/security/hr_expense_security.xml
odoo/addons/hr_expense_widget_o2m/static/description/icon.png
odoo/addons/hr_expense_widget_o2m/static/description/index.html
odoo/addons/hr_expense_widget_o2m/views/hr_expense_views.xml
odoo/addons/hr_expense_widget_o2m/views/res_config_settings_views.xml
odoo14_addon_hr_expense_widget_o2m-14.0.1.0.1.dev8.dist-info/METADATA
odoo14_addon_hr_expense_widget_o2m-14.0.1.0.1.dev8.dist-info/WHEEL
odoo14_addon_hr_expense_widget_o2m-14.0.1.0.1.dev8.dist-info/top_level.txt
odoo14_addon_hr_expense_widget_o2m-14.0.1.0.1.dev8.dist-info/RECORD
